mesop/__init__.py
mesop/example_index.py
mesop/py.typed
mesop/version.py
mesop/bin/__init__.py
mesop/bin/bin.py
mesop/cli/__init__.py
mesop/cli/execute_module.py
mesop/colab/__init__.py
mesop/colab/colab_run.py
mesop/colab/colab_run_test.py
mesop/colab/colab_show.py
mesop/commands/__init__.py
mesop/commands/focus_component.py
mesop/commands/navigate.py
mesop/commands/scroll_into_view.py
mesop/commands/set_page_title.py
mesop/component_helpers/__init__.py
mesop/component_helpers/diff_component_test.py
mesop/component_helpers/helper.py
mesop/component_helpers/helper_test.py
mesop/component_helpers/style.py
mesop/component_helpers/web_component.py
mesop/components/__init__.py
mesop/components/accordion/__init__.py
mesop/components/accordion/accordion.py
mesop/components/accordion/accordion_pb2.py
mesop/components/accordion/accordion_pb2.pyi
mesop/components/audio/__init__.py
mesop/components/audio/audio.py
mesop/components/audio/audio_pb2.py
mesop/components/audio/audio_pb2.pyi
mesop/components/audio/e2e/__init__.py
mesop/components/audio/e2e/audio_app.py
mesop/components/autocomplete/__init__.py
mesop/components/autocomplete/autocomplete.py
mesop/components/autocomplete/autocomplete_pb2.py
mesop/components/autocomplete/autocomplete_pb2.pyi
mesop/components/autocomplete/e2e/__init__.py
mesop/components/autocomplete/e2e/autocomplete_app.py
mesop/components/badge/__init__.py
mesop/components/badge/badge.py
mesop/components/badge/badge_pb2.py
mesop/components/badge/badge_pb2.pyi
mesop/components/badge/e2e/__init__.py
mesop/components/badge/e2e/badge_app.py
mesop/components/box/__init__.py
mesop/components/box/box.py
mesop/components/box/box_pb2.py
mesop/components/box/box_pb2.pyi
mesop/components/box/e2e/__init__.py
mesop/components/box/e2e/box_app.py
mesop/components/box/e2e/box_events_app.py
mesop/components/button/__init__.py
mesop/components/button/button.py
mesop/components/button/button_pb2.py
mesop/components/button/button_pb2.pyi
mesop-1.2.0.dist-info/licenses/LICENSE
mesop-1.2.0.dist-info/METADATA
mesop-1.2.0.dist-info/WHEEL
mesop-1.2.0.dist-info/entry_points.txt
mesop-1.2.0.dist-info/top_level.txt
mesop-1.2.0.dist-info/RECORD
