Metadata-Version: 2.4
Name: mesop
Version: 1.2.0
Summary: Build UIs in Python
Home-page: https://github.com/mesop-dev/mesop
Author: Google Inc.
License: Apache 2.0
Keywords: mesop
Classifier: Development Status :: 4 - Beta
Classifier: Intended Audience :: Developers
Classifier: License :: OSI Approved :: Apache Software License
Classifier: Programming Language :: Python :: 3
Classifier: Programming Language :: Python :: 3.10
Classifier: Programming Language :: Python :: 3.11
Classifier: Programming Language :: Python :: 3 :: Only
Classifier: Topic :: Software Development :: Libraries :: Python Modules
Classifier: Topic :: Software Development :: Libraries
Requires-Python: >=3.10
License-File: LICENSE
Requires-Dist: absl-py
Requires-Dist: deepdiff<9,>=8.6.1
Requires-Dist: flask
Requires-Dist: msgpack
Requires-Dist: protobuf
Requires-Dist: pydantic
Requires-Dist: python-dotenv
Requires-Dist: watchdog
Requires-Dist: werkzeug>=3.0.6
Dynamic: author
Dynamic: classifier
Dynamic: description
Dynamic: home-page
Dynamic: keywords
Dynamic: license
Dynamic: license-file
Dynamic: requires-dist
Dynamic: requires-python
Dynamic: summary
